{
  "version": "1.0",
  "data": {
    "channel": [
      {
        "id": "38ea273c889895aee5cb838a2fcd0d13",
        "name": "Sony Entertainment",
        "logo": "https://d250n7duzgh7t2.cloudfront.net/5M1kWBEAJqxy2bmbnRVNZU9RkqFj0cmS/7718F46772A54819AE19147BCE9D3D6B/tg/Sony_Entertainment_225x225-1731319732611.png",
        "schedule": [
          {
            "start_date_time": "20241213090000",
            "end_date_time": "20241213100000",
            "lang": "en",
            "title": "Program 1",
            "description": "Science documentary.",
            "start": "2024-12-18 00:00:00",
            "end": "2024-12-18 00:29:59"
          },
          {
            "start_date_time": "20241213090000",
            "end_date_time": "20241213100000",
            "lang": "en",
            "title": "Program 2",
            "description": "Science documentary.",
            "start": "2024-12-18 00:30:00",
            "end": "2024-12-18 00:59:59"
          },
          {
            "start_date_time": "20241213090000",
            "end_date_time": "20241213100000",
            "lang": "en",
            "title": "Program 3",
            "description": "Science documentary.",
            "start": "2024-12-18 01:00:00",
            "end": "2024-12-18 01:29:59"
          },
          {
            "start_date_time": "20241213090000",
            "end_date_time": "20241213100000",
            "lang": "en",
            "title": "Program 4",
            "description": "Science documentary.",
            "start": "2024-12-18 01:30:00",
            "end": "2024-12-18 01:59:59"
          },
          {
            "start_date_time": "20241213090000",
            "end_date_time": "20241213100000",
            "lang": "en",
            "title": "Program 5",
            "description": "Science documentary.",
            "start": "2024-12-18 02:00:00",
            "end": "2024-12-18 02:29:59"
          },
          {
            "start_date_time": "20241213090000",
            "end_date_time": "20241213100000",
            "lang": "en",
            "title": "Program 6",
            "description": "Science documentary.",
            "start": "2024-12-18 02:30:00",
            "end": "2024-12-18 02:59:59"
          },
          {
            "start_date_time": "20241213090000",
            "end_date_time": "20241213100000",
            "lang": "en",
            "title": "Program 7",
            "description": "Science documentary.",
            "start": "2024-12-18 03:00:00",
            "end": "2024-12-18 03:29:59"
          },
          {
            "start_date_time": "20241213090000",
            "end_date_time": "20241213100000",
            "lang": "en",
            "title": "Program 8",
            "description": "Science documentary.",
            "start": "2024-12-18 03:30:00",
            "end": "2024-12-18 03:59:59"
          },
          {
            "start_date_time": "20241213090000",
            "end_date_time": "20241213100000",
            "lang": "en",
            "title": "Program 9",
            "description": "Science documentary.",
            "start": "2024-12-18 04:00:00",
            "end": "2024-12-18 04:29:59"
          },
          {
            "start_date_time": "20241213090000",
            "end_date_time": "20241213100000",
            "lang": "en",
            "title": "Program 10",
            "description": "Science documentary.",
            "start": "2024-12-18 04:30:00",
            "end": "2024-12-18 04:59:59"
          },
          {
            "start_date_time": "20241213090000",
            "end_date_time": "20241213100000",
            "lang": "en",
            "title": "Program 11",
            "description": "Science documentary.",
            "start": "2024-12-18 05:00:00",
            "end": "2024-12-18 05:29:59"
          },
          {
            "start_date_time": "20241213090000",
            "end_date_time": "20241213100000",
            "lang": "en",
            "title": "Program 12",
            "description": "Science documentary.",
            "start": "2024-12-18 05:30:00",
            "end": "2024-12-18 05:59:59"
          },
          {
            "start_date_time": "20241213090000",
            "end_date_time": "20241213100000",
            "lang": "en",
            "title": "Program 13",
            "description": "Science documentary.",
            "start": "2024-12-18 06:00:00",
            "end": "2024-12-18 06:29:59"
          },
          {
            "start_date_time": "20241213090000",
            "end_date_time": "20241213100000",
            "lang": "en",
            "title": "Program 14",
            "description": "Science documentary.",
            "start": "2024-12-18 06:30:00",
            "end": "2024-12-18 06:59:59"
          },
          {
            "start_date_time": "20241213090000",
            "end_date_time": "20241213100000",
            "lang": "en",
            "title": "Program 15",
            "description": "Science documentary.",
            "start": "2024-12-18 07:00:00",
            "end": "2024-12-18 07:29:59"
          },
          {
            "start_date_time": "20241213090000",
            "end_date_time": "20241213100000",
            "lang": "en",
            "title": "Program 16",
            "description": "Science documentary.",
            "start": "2024-12-18 07:30:00",
            "end": "2024-12-18 07:59:59"
          },
          {
            "start_date_time": "20241213090000",
            "end_date_time": "20241213100000",
            "lang": "en",
            "title": "Program 17",
            "description": "Science documentary.",
            "start": "2024-12-18 08:00:00",
            "end": "2024-12-18 08:29:59"
          },
          {
            "start_date_time": "20241213090000",
            "end_date_time": "20241213100000",
            "lang": "en",
            "title": "Program 18",
            "description": "Science documentary.",
            "start": "2024-12-18 08:30:00",
            "end": "2024-12-18 08:59:59"
          },
          {
            "start_date_time": "20241213090000",
            "end_date_time": "20241213100000",
            "lang": "en",
            "title": "Program 19",
            "description": "Science documentary.",
            "start": "2024-12-18 09:00:00",
            "end": "2024-12-18 09:29:59"
          },
          {
            "start_date_time": "20241213090000",
            "end_date_time": "20241213100000",
            "lang": "en",
            "title": "Program 20",
            "description": "Science documentary.",
            "start": "2024-12-18 09:30:00",
            "end": "2024-12-18 09:59:59"
          },
          {
            "start_date_time": "20241213090000",
            "end_date_time": "20241213100000",
            "lang": "en",
            "title": "Program 21",
            "description": "Science documentary.",
            "start": "2024-12-18 10:00:00",
            "end": "2024-12-18 23:59:59"
          }
        ]
      }
    ]
  }
}
